testPackFunc/__init__.py
testpackageeeeeee-0.1.dist-info/LICENSE.txt
testpackageeeeeee-0.1.dist-info/METADATA
testpackageeeeeee-0.1.dist-info/WHEEL
testpackageeeeeee-0.1.dist-info/top_level.txt
testpackageeeeeee-0.1.dist-info/RECORD
