Metadata-Version: 2.1
Name: testpackageeeeeee
Version: 0.1
Summary: package for testing
Author: bharat
Author-email: bharat.singh.1908@gmail.com
Classifier: Programming Language :: Python :: 3
Classifier: License :: OSI Approved :: MIT License
Classifier: Operating System :: OS Independent
License-File: LICENSE.txt
